antchain_sdk_ak_9468e09a21e84cc8b9a8d4a2de18c792/__init__.py
antchain_sdk_ak_9468e09a21e84cc8b9a8d4a2de18c792/client.py
antchain_sdk_ak_9468e09a21e84cc8b9a8d4a2de18c792/models.py
antchain_ak_9468e09a21e84cc8b9a8d4a2de18c792-1.0.2.dist-info/LICENSE
antchain_ak_9468e09a21e84cc8b9a8d4a2de18c792-1.0.2.dist-info/METADATA
antchain_ak_9468e09a21e84cc8b9a8d4a2de18c792-1.0.2.dist-info/WHEEL
antchain_ak_9468e09a21e84cc8b9a8d4a2de18c792-1.0.2.dist-info/top_level.txt
antchain_ak_9468e09a21e84cc8b9a8d4a2de18c792-1.0.2.dist-info/RECORD
